greml/__main__.py
greml/__version__.py
greml-1.3.0.dist-info/METADATA
greml-1.3.0.dist-info/WHEEL
greml-1.3.0.dist-info/entry_points.txt
greml-1.3.0.dist-info/RECORD
