Metadata-Version: 2.4
Name: greml
Version: 1.3.0
Summary: A CLI tool to make HTML greppable
Author-email: Adam McKay <adam@beepboop.digital>
Requires-Python: >=3.10
Requires-Dist: beautifulsoup4>=4.12.3
Requires-Dist: fake-useragent>=2.0.3
Requires-Dist: httpx>=0.26.0
Requires-Dist: rich>=13.6.0
Requires-Dist: typer>=0.9.0
Provides-Extra: dev
Requires-Dist: pytest>=8.0.0; extra == 'dev'
Requires-Dist: ruff>=0.2.0; extra == 'dev'
